fmus_zllm-0.0.1.dist-info/licenses/LICENSE
zllm/__init__.py
zllm/__main__.py
zllm/base.py
zllm/cli.py
zllm/client.py
zllm/context_manager.py
zllm/exceptions.py
zllm/integration.py
zllm/key_manager.py
zllm/message.py
zllm/model_registry.py
zllm/config/__init__.py
zllm/config/config_manager.py
zllm/config/default_config.py
zllm/providers/__init__.py
zllm/providers/anthropic.py
zllm/providers/cerebras.py
zllm/providers/cohere.py
zllm/providers/gemini.py
zllm/providers/glhf.py
zllm/providers/groq.py
zllm/providers/huggingface.py
zllm/providers/hyperbolic.py
zllm/providers/openai.py
zllm/providers/provider_map.py
zllm/providers/sambanova.py
zllm/providers/together.py
zllm/utils/__init__.py
zllm/utils/logging.py
zllm/utils/parsing.py
fmus_zllm-0.0.1.dist-info/METADATA
fmus_zllm-0.0.1.dist-info/WHEEL
fmus_zllm-0.0.1.dist-info/entry_points.txt
fmus_zllm-0.0.1.dist-info/top_level.txt
fmus_zllm-0.0.1.dist-info/RECORD
