Metadata-Version: 2.4
Name: fmus-zllm
Version: 0.0.1
Summary: A simple, unified interface for multiple LLM providers
Author-email: mexyusef <yusef314159@gmail.com>
Project-URL: Homepage, https://github.com/mexyusef/zllm
Project-URL: Issues, https://github.com/mexyusef/zllm/issues
Classifier: Programming Language :: Python :: 3
Classifier: License :: OSI Approved :: MIT License
Classifier: Operating System :: OS Independent
Requires-Python: >=3.8
License-File: LICENSE
Requires-Dist: aiohttp>=3.8.0
Requires-Dist: pyyaml>=6.0
Requires-Dist: openai>=1.0.0
Requires-Dist: anthropic>=0.5.0
Requires-Dist: google-generativeai>=0.3.0
Requires-Dist: groq>=0.4.0
Requires-Dist: cohere>=4.0.0
Provides-Extra: huggingface
Requires-Dist: huggingface_hub>=0.19.0; extra == "huggingface"
Provides-Extra: examples
Requires-Dist: rich>=13.0.0; extra == "examples"
Provides-Extra: all
Requires-Dist: huggingface_hub>=0.19.0; extra == "all"
Requires-Dist: rich>=13.0.0; extra == "all"
Dynamic: license-file
